drf_jsonschema/__init__.py
drf_jsonschema/_validators.py
drf_jsonschema/apps.py
drf_jsonschema/exceptions.py
drf_jsonschema/fields.py
drf_jsonschema/serializers.py
drf_jsonschema/validators.py
drf_jsonschema/migrations/__init__.py
drf_jsonschema/tests/__init__.py
drf_jsonschema/tests/models.py
drf_jsonschema/tests/serializers.py
drf_jsonschema/tests/test_json_schema_field_validator.py
drf_jsonschema/tests/test_views.py
drf_jsonschema/tests/views.py
drf_jsonschema-0.2.2.dist-info/LICENSE
drf_jsonschema-0.2.2.dist-info/METADATA
drf_jsonschema-0.2.2.dist-info/WHEEL
drf_jsonschema-0.2.2.dist-info/top_level.txt
drf_jsonschema-0.2.2.dist-info/RECORD
