Metadata-Version: 2.1
Name: drf-jsonschema
Version: 0.2.2
Summary: A package that constructs JsonSchema validation error into error tree for Django Rest Framework with custom error message in compliance with the DRF error message.
License: MIT License
Keywords: jsonschema,drf
Requires-Python: >=3.8
License-File: LICENSE
Requires-Dist: jsonschema (>=4.16.0)
